CHANGELOG.md
LICENSE
MANIFEST.in
Makefile
README.rst
requirements.txt
setup.cfg
setup.py
docs/.nojekyll
docs/index.html
docs/objects.inv
docs/_static/ajax-loader.gif
docs/_static/alabaster.css
docs/_static/basic.css
docs/_static/comment-bright.png
docs/_static/comment-close.png
docs/_static/comment.png
docs/_static/custom.css
docs/_static/doctools.js
docs/_static/down-pressed.png
docs/_static/down.png
docs/_static/file.png
docs/_static/jquery-3.1.0.js
docs/_static/jquery.js
docs/_static/minus.png
docs/_static/plus.png
docs/_static/pygments.css
docs/_static/searchtools.js
docs/_static/underscore-1.3.1.js
docs/_static/underscore.js
docs/_static/up-pressed.png
docs/_static/up.png
docs/_static/websupport.js
ezrecords/__init__.py
ezrecords/abstractdb.py
ezrecords/cli.py
ezrecords/compat.py
ezrecords/mysqldb.py
ezrecords/postgresdb.py
ezrecords/records.py
ezrecords/sqlitedb.py
ezrecords/util.py
ezrecords.egg-info/PKG-INFO
ezrecords.egg-info/SOURCES.txt
ezrecords.egg-info/dependency_links.txt
ezrecords.egg-info/entry_points.txt
ezrecords.egg-info/not-zip-safe
ezrecords.egg-info/requires.txt
ezrecords.egg-info/top_level.txt
tests/.DS_Store
tests/__init__.py
tests/sample_query.sql
tests/test_ezrecords.py
tests/test_mysqldb.py
tests/test_postgresdb.py
tests/test_sqlitedb.py
tests/test_util.py
tests/__pycache__/.DS_Store