Metadata-Version: 1.1
Name: ezrecords
Version: 0.3.0
Summary: SQL for the enhanced.
Home-page: https://github.com/dareenzo/ezrecords
Author: Paulo Phagula
Author-email: pphagula@gmail.com
License: MIT
Keywords: database,db,helper,utility,sql
Platform: a
Platform: n
Platform: y
Classifier: Development Status :: 4 - Beta
Classifier: Intended Audience :: Developers
Classifier: License :: OSI Approved :: MIT License
Classifier: Operating System :: OS Independent
Classifier: Programming Language :: Python
Classifier: Topic :: Software Development
Classifier: Topic :: Software Development :: Libraries
Classifier: Topic :: Database
Classifier: Topic :: Utilities
